fedcore/__init__.py
fedcore/algorithm/__init__.py
fedcore/algorithm/base_compression_model.py
fedcore/algorithm/distillation/__init__.py
fedcore/algorithm/distillation/distilator.py
fedcore/algorithm/distillation/hooks.py
fedcore/algorithm/low_rank/__init__.py
fedcore/algorithm/low_rank/decomposer.py
fedcore/algorithm/low_rank/hooks.py
fedcore/algorithm/low_rank/low_rank_opt.py
fedcore/algorithm/low_rank/rank_distortion.py
fedcore/algorithm/low_rank/rank_pruning.py
fedcore/algorithm/low_rank/svd_tools.py
fedcore/algorithm/pruning/__init__.py
fedcore/algorithm/pruning/hooks.py
fedcore/algorithm/pruning/pruners.py
fedcore/algorithm/pruning/pruning_validation.py
fedcore/algorithm/pruning/sfp_tools.py
fedcore/algorithm/quantization/__init__.py
fedcore/algorithm/quantization/hooks.py
fedcore/algorithm/quantization/quantizers.py
fedcore/algorithm/quantization/utils.py
fedcore/api/__init__.py
fedcore/api/api_configs.py
fedcore/api/config_factory.py
fedcore/api/main.py
fedcore/api/utils/__init__.py
fedcore/api/utils/api_init.py
fedcore/api/utils/checkers_collection.py
fedcore/api/utils/data.py
fedcore/api/utils/evaluation.py
fedcore/api/utils/misc.py
fedcore/architecture/__init__.py
fedcore/architecture/abstraction/__init__.py
fedcore/architecture/abstraction/accessor.py
fedcore/architecture/abstraction/decorators.py
fedcore/architecture/abstraction/delegator.py
fedcore/architecture/abstraction/placeholders.py
fedcore/architecture/comptutaional/__init__.py
fedcore/architecture/comptutaional/devices.py
fedcore/architecture/dataset/__init__.py
fedcore/architecture/dataset/api_loader.py
fedcore/architecture/dataset/custom_loader.py
fedcore/architecture/dataset/datasets_from_source.py
fedcore/architecture/dataset/splitters.py
fedcore/architecture/dataset/utils.py
fedcore/architecture/dataset/task_specified/__init__.py
fedcore/architecture/dataset/task_specified/classification_datasets.py
fedcore/architecture/dataset/task_specified/dummy_clf.py
fedcore-0.0.5.3.dist-info/METADATA
fedcore-0.0.5.3.dist-info/WHEEL
fedcore-0.0.5.3.dist-info/top_level.txt
fedcore-0.0.5.3.dist-info/RECORD
